lrsplines.cpython-312-i386-linux-gnu.so
.gitignore
lrspline/raw.pyi
lrspline/raw.cpython-312-i386-linux-gnu.so
lrspline/raw.pyx
lrspline/__init__.py
lrspline/raw.cpp
lrspline/py.typed
lrsplines-1.13.0.dist-info/METADATA
lrsplines-1.13.0.dist-info/WHEEL
lrsplines-1.13.0.dist-info/RECORD
lrsplines-1.13.0.dist-info/licenses/COPYING
lrsplines-1.13.0.dist-info/licenses/LICENSE
