Metadata-Version: 2.1
Name: lrsplines
Version: 1.13.0
Summary: Python bindings for the LRSplines library
Author-Email: Eivind Fonn <eivind.fonn@sintef.no>
License: GPL-3-or-later
Requires-Python: <4.0,>=3.9
Requires-Dist: numpy>=1.23
